MANIFEST.in
README.rst
requirements-tests.txt
requirements.txt
setup.py
flickr_pony/__init__.py
flickr_pony/models.py
flickr_pony/storage.py
flickr_pony.egg-info/PKG-INFO
flickr_pony.egg-info/SOURCES.txt
flickr_pony.egg-info/dependency_links.txt
flickr_pony.egg-info/requires.txt
flickr_pony.egg-info/top_level.txt
flickr_pony/tests/__init__.py
flickr_pony/tests/fixtures.py
flickr_pony/tests/test_storage.py
test_project/manage.py
test_project/test_project/__init__.py
test_project/test_project/settings.py
test_project/test_project/urls.py
test_project/test_project/wsgi.py